deepparameters/__init__.py
deepparameters/architectures.py
deepparameters/core.py
deepparameters/parallel.py
deepparameters/sampling.py
deepparameters/utils.py
deepparameters-2.0.6.dist-info/METADATA
deepparameters-2.0.6.dist-info/WHEEL
deepparameters-2.0.6.dist-info/top_level.txt
deepparameters-2.0.6.dist-info/RECORD
