Metadata-Version: 2.4
Name: deepparameters
Version: 2.0.6
Summary: Advanced Neural Network CPD Learning for Bayesian Networks with Configurable Parallel Execution Styles - Beta
Author-email: Rudzani Mulaudzi <rudzani.mulaudzi2@students.wits.ac.za>
Maintainer-email: Rudzani Mulaudzi <rudzani.mulaudzi2@students.wits.ac.za>
License-Expression: MIT
Project-URL: Homepage, https://github.com/rudzanimulaudzi/DeepParameters
Project-URL: Repository, https://github.com/rudzanimulaudzi/DeepParameters
Project-URL: Documentation, https://github.com/rudzanimulaudzi/DeepParameters#readme
Project-URL: Bug Tracker, https://github.com/rudzanimulaudzi/DeepParameters/issues
Project-URL: Source Code, https://github.com/rudzanimulaudzi/DeepParameters
Keywords: bayesian networks,neural networks,cpd learning,deep learning,probabilistic modeling,parameter learning,pgmpy,parallel learning,beta
Classifier: Development Status :: 4 - Beta
Classifier: Intended Audience :: Developers
Classifier: Intended Audience :: Science/Research
Classifier: Programming Language :: Python :: 3
Classifier: Programming Language :: Python :: 3.8
Classifier: Programming Language :: Python :: 3.9
Classifier: Programming Language :: Python :: 3.10
Classifier: Programming Language :: Python :: 3.11
Classifier: Topic :: Scientific/Engineering :: Artificial Intelligence
Classifier: Topic :: Software Development :: Libraries :: Python Modules
Requires-Python: >=3.8
Requires-Dist: numpy<2.0.0,>=1.19.0
Requires-Dist: scikit-learn>=1.0.0
Requires-Dist: matplotlib>=3.3.0
Requires-Dist: seaborn>=0.11.0
Requires-Dist: pandas>=1.3.0
Requires-Dist: pgmpy>=0.1.17
Requires-Dist: networkx>=2.6.0
Provides-Extra: tensorflow
Requires-Dist: tensorflow>=2.8.0; extra == "tensorflow"
Provides-Extra: dev
Requires-Dist: pytest>=7.0.0; extra == "dev"
Requires-Dist: pytest-cov>=4.0.0; extra == "dev"
Requires-Dist: black>=22.0.0; extra == "dev"
Requires-Dist: isort>=5.10.0; extra == "dev"
Requires-Dist: mypy>=0.991; extra == "dev"
